[
  {
    "id": "device-001",
    "nickname": "GrowBag-A1",
    "status": "active",
    "lastPing": "2024-01-15T10:30:00Z",
    "rssi": -65,
    "battery": 85,
    "healthScore": 98,
    "firmwareVersion": "v2.1.3",
    "location": "Grow Bag 1",
    "uptime": "15 days"
  },
  {
    "id": "device-002",
    "nickname": "GrowBag-A2",
    "status": "active",
    "lastPing": "2024-01-15T10:29:45Z",
    "rssi": -72,
    "battery": 92,
    "healthScore": 95,
    "firmwareVersion": "v2.1.3",
    "location": "Grow Bag 2",
    "uptime": "12 days"
  },
  {
    "id": "device-003",
    "nickname": "GrowBag-B1",
    "status": "warning",
    "lastPing": "2024-01-15T10:25:12Z",
    "rssi": -78,
    "battery": 45,
    "healthScore": 72,
    "firmwareVersion": "v2.0.8",
    "location": "Grow Bag 3",
    "uptime": "8 days"
  },
  {
    "id": "device-004",
    "nickname": "GrowBag-B2",
    "status": "active",
    "lastPing": "2024-01-15T10:30:15Z",
    "rssi": -68,
    "battery": 78,
    "healthScore": 89,
    "firmwareVersion": "v2.1.3",
    "location": "Grow Bag 4",
    "uptime": "20 days"
  },
  {
    "id": "device-005",
    "nickname": "GrowBag-C1",
    "status": "inactive",
    "lastPing": "2024-01-15T08:45:30Z",
    "rssi": -85,
    "battery": 12,
    "healthScore": 25,
    "firmwareVersion": "v2.0.5",
    "location": "Grow Bag 5",
    "uptime": "0 days"
  },
  {
    "id": "device-006",
    "nickname": "GrowBag-C2",
    "status": "active",
    "lastPing": "2024-01-15T10:29:58Z",
    "rssi": -70,
    "battery": 88,
    "healthScore": 94,
    "firmwareVersion": "v2.1.3",
    "location": "Grow Bag 6",
    "uptime": "18 days"
  },
  {
    "id": "device-007",
    "nickname": "Environmental-Hub",
    "status": "active",
    "lastPing": "2024-01-15T10:30:05Z",
    "rssi": -55,
    "battery": 100,
    "healthScore": 100,
    "firmwareVersion": "v3.0.1",
    "location": "Central Hub",
    "uptime": "45 days"
  },
  {
    "id": "device-008",
    "nickname": "Nutrient-Pump-A",
    "status": "warning",
    "lastPing": "2024-01-15T10:28:22Z",
    "rssi": -75,
    "battery": 65,
    "healthScore": 78,
    "firmwareVersion": "v1.9.2",
    "location": "Pump Station A",
    "uptime": "5 days"
  }
]
